pulicast/__init__.py
pulicast/address.py
pulicast/channel.py
pulicast/channel_naming_conventions.py
pulicast/namespace.py
pulicast/node.py
pulicast/pulicast_qt.py
pulicast/pulicast_threaded.py
pulicast/pulicast_trio.py
pulicast/serialization.py
pulicast/core/__init__.py
pulicast/core/channel_hashing.py
pulicast/core/channel_store.py
pulicast/core/lead_extractor.py
pulicast/core/sequence_numbered_sender.py
pulicast/core/subscription_dispatcher.py
pulicast/core/transport.py
pulicast/core/utils/__init__.py
pulicast/core/utils/extract_from_bytearray.py
pulicast/core/utils/name_resolution.py
pulicast/core/utils/observable_container.py
pulicast/core/utils/observable_dict.py
pulicast/core/utils/observable_property.py
pulicast/core/utils/observable_set.py
pulicast/discovery/__init__.py
pulicast/discovery/channel_discoverer.py
pulicast/discovery/channel_view.py
pulicast/discovery/node_discoverer.py
pulicast/discovery/node_view.py
pulicast/transport/__init__.py
pulicast/transport/plain_socket_transport.py
pulicast/transport/qt_multicast_transport.py
pulicast/transport/trio_multicast_transport.py
pulicast/transport/udp_transport.py
pulicast_messages/__init__.py
pulicast_messages/boolean_msg.py
pulicast_messages/byte_msg.py
pulicast_messages/double_msg.py
pulicast_messages/float_msg.py
pulicast_messages/int16_msg.py
pulicast_messages/int32_msg.py
pulicast_messages/int64_msg.py
pulicast_messages/int8_msg.py
pulicast_messages/ping.py
pulicast_messages/poke_setting.py
pulicast_messages/pulicast_channel.py
pulicast_messages/pulicast_node.py
pulicast_messages/reset_setting_to_default.py
pulicast_messages/roc_ack.py
pulicast_messages/string_msg.py
pulicast_messages/unset_setting.py
pulicast_tools/__init__.py
pulicast_tools/puliconf/__init__.py
pulicast_tools/puliconf/channel_naming_conventions.py
pulicast_tools/puliconf/cli.py
pulicast_tools/puliconf/setting.py
pulicast_tools/puliconf/setting_discoverer.py
pulicast_tools/puliconf/setting_view.py
pulicast_tools/puliconf/utils.py
pulicast-2.0.1.dist-info/LICENSE.txt
pulicast-2.0.1.dist-info/METADATA
pulicast-2.0.1.dist-info/WHEEL
pulicast-2.0.1.dist-info/entry_points.txt
pulicast-2.0.1.dist-info/top_level.txt
pulicast-2.0.1.dist-info/RECORD
